uv_workspace_codegen/__init__.py
uv_workspace_codegen/__main__.py
uv_workspace_codegen/main.py
uv_workspace_codegen/py.typed
uv_workspace_codegen/templates/package.template.yml
uv_workspace_codegen-0.6.0.dist-info/METADATA
uv_workspace_codegen-0.6.0.dist-info/WHEEL
uv_workspace_codegen-0.6.0.dist-info/entry_points.txt
uv_workspace_codegen-0.6.0.dist-info/RECORD
