Metadata-Version: 2.4
Name: uv-workspace-codegen
Version: 0.6.0
Summary: Generate individual CI/CD workflows for packages in the workspace
Requires-Python: >=3.12
Requires-Dist: click>=8.1.7
Requires-Dist: jinja2-ansible-filters>=1.3.2
Requires-Dist: jinja2>=3.1.6
Requires-Dist: pyyaml>=6.0.1
